[
    {
        "id": "19184",
        "name": "Redmi Note 13 Pro",
        "price": "1199",
        "count": 1500732
    },
    {
        "id": "19182",
        "name": "Redmi Note 13 5G",
        "price": "899",
        "count": 903201
    },
    {
        "id": "19185",
        "name": "Redmi Note 13 Pro+",
        "price": "1999",
        "count": 506907
    },
    {
        "id": "19054",
        "name": "Redmi 12 5G",
        "price": "949",
        "count": 28996
    },
    {
        "id": "19019",
        "name": "Xiaomi MIX Fold 3",
        "price": "6999",
        "count": 156677
    },
    {
        "id": "16337",
        "name": "Xiaomi MIX Fold 2",
        "price": "8999",
        "count": 137374
    },
    {
        "id": "19019",
        "name": "Xiaomi MIX Fold 3",
        "price": "6999",
        "count": 156677
    },
    {
        "id": "16337",
        "name": "Xiaomi MIX Fold 2",
        "price": "8999",
        "count": 137374
    },
    {
        "id": "17971",
        "name": "Xiaomi 13",
        "price": "2699",
        "count": 1623984
    },
    {
        "id": "17972",
        "name": "Xiaomi 13 限量定制色",
        "price": "3299",
        "count": 34588
    },
    {
        "id": "17969",
        "name": "Xiaomi 13 Pro",
        "price": "4599",
        "count": 328271
    },
    {
        "id": "18363",
        "name": "Xiaomi 13 Ultra",
        "price": "3999",
        "count": 305881
    },
    {
        "id": "18443",
        "name": "Xiaomi 13 Ultra 限量定制色",
        "price": "4499",
        "count": 7086
    },
    {
        "id": "18075",
        "name": "Redmi K60",
        "price": "2499",
        "count": 1545925
    },
    {
        "id": "18077",
        "name": "Redmi K60 Pro",
        "price": "3299",
        "count": 248741
    },
    {
        "id": "18073",
        "name": "Redmi K60E",
        "price": "1899",
        "count": 107583
    },
    {
        "id": "18482",
        "name": "Xiaomi Civi 3",
        "price": "2099",
        "count": 550359
    },
    {
        "id": "18569",
        "name": "Xiaomi Civi 3 迪士尼100周年限定版手机壳",
        "price": "99",
        "count": 2306
    },
    {
        "id": "16642",
        "name": "Redmi Note 12 5G",
        "price": "899",
        "count": 904905
    },
    {
        "id": "18268",
        "name": "Redmi Note 12 Turbo",
        "price": "1999",
        "count": 1265875
    },
    {
        "id": "18542",
        "name": "Redmi Note 12T Pro",
        "price": "1399",
        "count": 107588
    },
    {
        "id": "19300",
        "name": "Xiaomi 14",
        "price": "3999",
        "count": 2322344
    },
    {
        "id": "19288",
        "name": "Xiaomi 14 Pro",
        "price": "4599",
        "count": 1006119
    },
    {
        "id": "19683",
        "name": "Xiaomi 14 Ultra",
        "price": "5999",
        "count": 309952
    },
    {
        "id": "20153",
        "name": "Redmi K70 至尊版",
        "price": "2599",
        "count": 776711
    },
    {
        "id": "19432",
        "name": "Redmi K70",
        "price": "2199",
        "count": 1440232
    },
    {
        "id": "19436",
        "name": "Redmi K70 Pro",
        "price": "2799",
        "count": 373835
    },
    {
        "id": "19437",
        "name": "Redmi K70E",
        "price": "1799",
        "count": 483488
    },
    {
        "id": "19752",
        "name": "Xiaomi Civi 4 Pro",
        "price": "2799",
        "count": 361989
    },
    {
        "id": "19835",
        "name": "Redmi Turbo 3",
        "price": "1699",
        "count": 800522
    },
    {
        "id": "20191",
        "name": "Xiaomi MIX Flip",
        "price": "5999",
        "count": 151391
    },
    {
        "id": "20181",
        "name": "Xiaomi MIX Fold 4",
        "price": "8999",
        "count": 74213
    },
    {
        "id": "20425",
        "name": "Redmi Note 14 Pro+",
        "price": "1899",
        "count": 420518
    },
    {
        "id": "20419",
        "name": "Redmi Note 14 Pro",
        "price": "1399",
        "count": 262941
    },
    {
        "id": "20420",
        "name": "Redmi Note 14 5G",
        "price": "1099",
        "count": 81338
    },
    {
        "id": "20618",
        "name": "Xiaomi 15",
        "price": "4499",
        "count": 278823
    },
    {
        "id": "20603",
        "name": "Xiaomi 15 Pro",
        "price": "5299",
        "count": 161783
    },
    {
        "id": "20609",
        "name": "Xiaomi 15 定制版",
        "price": "4999",
        "count": 6409
    }
]